job_scraper/__init__.py
job_scraper/scraper.py
job_scraper_lib-0.1.dist-info/METADATA
job_scraper_lib-0.1.dist-info/WHEEL
job_scraper_lib-0.1.dist-info/entry_points.txt
job_scraper_lib-0.1.dist-info/top_level.txt
job_scraper_lib-0.1.dist-info/RECORD
