Metadata-Version: 2.2
Name: job_scraper_lib
Version: 0.1
Summary: A Python library for scraping job listings from company career pages
Home-page: https://github.com/yourusername/job_scraper_lib
Author: Avanish Singh
Author-email: suryanshskcontact@gmail.com
Classifier: Programming Language :: Python :: 3
Classifier: License :: OSI Approved :: MIT License
Classifier: Operating System :: OS Independent
Requires-Python: >=3.6
Requires-Dist: selenium
Requires-Dist: webdriver_manager
Dynamic: author
Dynamic: author-email
Dynamic: classifier
Dynamic: description
Dynamic: description-content-type
Dynamic: home-page
Dynamic: requires-dist
Dynamic: requires-python
Dynamic: summary
